ImageInputHandler/ImageInputHandler.py
ImageInputHandler/__init__.py
universal_image_input_handler-0.1.0.dist-info/METADATA
universal_image_input_handler-0.1.0.dist-info/WHEEL
universal_image_input_handler-0.1.0.dist-info/top_level.txt
universal_image_input_handler-0.1.0.dist-info/RECORD
